Workbook
Name Slicer_order_date: #N/A
Name Slicer_product_ID: #N/A
Name Slicer_product_name: #N/A
Name Slicer_product_name1: #N/A
Name Slicer_tabl_product.category: #N/A
Name Slicer_tabl_product.category1: #N/A

Sheet Orders_tbl
A1: Order_ID | B1: order_date | C1: order_time | D1: product_ID | E1: product_name | F1: Quantity | G1: Price | H1: Discount | I1: Amount Afte Discount | J1: GST | K1: Delivery Charges | L1: Total Received Amount | M1: Delivery_status
A2: 318778 | B2: 2026-03-01 | C2: 14:03:75 | D2: =_xlfn.XLOOKUP(E2,product_tbl!B1:B27,product_tbl!A1:A27,"no id found",0) -> V201 | E2: CHICKEN MOMOS | F2: 1 | G2: 120 | H2: 0 | I2: 120 | J2: 6 | K2: =L2-(I2+J2) -> 29 | L2: 155 | M2: SUCCESS
A3: 318836 | B3: 2026-03-01 | C3: 19:03:49 | D3: =_xlfn.XLOOKUP(E3,product_tbl!B2:B28,product_tbl!A2:A28,"no id found",0) -> V208 | E3: CHICKEN NUGGETS | F3: 2 | G3: 250 | H3: 0 | I3: 250 | J3: 12.5 | K3: =L3-(I3+J3) -> 19 | L3: 281.5 | M3: SUCCESS
A4: 321207 | B4: 2026-03-17 | C4: 14:03:60 | D4: =_xlfn.XLOOKUP(E4,product_tbl!B3:B29,product_tbl!A3:A29,"no id found",0) -> V107 | E4: VEG-KURKURE MOMOS | F4: 2 | G4: 240 | H4: 0 | I4: 240 | J4: 12 | K4: =L4-(I4+J4) -> 19 | L4: 271 | M4: SUCCESS
A5: 321436 | B5: 2026-03-18 | C5: 19:03:97 | D5: =_xlfn.XLOOKUP(E5,product_tbl!B4:B30,product_tbl!A4:A30,"no id found",0) -> V110 | E5: VEG FINGERS | F5: 1 | G5: 220 | H5: 0 | I5: 220 | J5: 11 | K5: =L5-(I5+J5) -> 19 | L5: 250 | M5: SUCCESS
A6: 321570 | B6: 2026-03-19 | C6: 18:03:99 | D6: =_xlfn.XLOOKUP(E6,product_tbl!B5:B31,product_tbl!A5:A31,"no id found",0) -> V212 | E6: CHICKEN LOLLIPOP | F6: 2 | G6: 280 | H6: 0 | I6: 280 | J6: 14 | K6: =L6-(I6+J6) -> 19 | L6: 313 | M6: SUCCESS
A7: 321893 | B7: 2026-03-21 | C7: 19:03:93 | D7: =_xlfn.XLOOKUP(E7,product_tbl!B6:B32,product_tbl!A6:A32,"no id found",0) -> V204 | E7: CHICKEN TIKKA MOMOS | F7: 1 | G7: 120 | H7: 0 | I7: 120 | J7: 6 | K7: =L7-(I7+J7) -> 29 | L7: 155 | M7: SUCCESS
A8: 321991 | B8: 2026-03-22 | C8: 12:03:56 | D8: =_xlfn.XLOOKUP(E8,product_tbl!B:B,product_tbl!A:A,"NO ID FOUND",0) -> V101 | E8: CORN MOMOS | F8: 1 | G8: 90 | H8: 0 | I8: 90 | J8: 4.5 | K8: =L8-(I8+J8) -> 37 | L8: 131.5 | M8: SUCCESS
A9: 322084 | B9: 2026-03-22 | C9: 20:03:54 | D9: =_xlfn.XLOOKUP(E9,product_tbl!B:B,product_tbl!A:A,"NO ID FOUND",0) -> V106 | E9: PANEER TIKKA MOMOS | F9: 2 | G9: 200 | H9: 0 | I9: 200 | J9: 10 | K9: =L9-(I9+J9) -> 27 | L9: 237 | M9: SUCCESS
A10: 322268 | B10: 2026-03-24 | C10: 16:03:14 | D10: =_xlfn.XLOOKUP(E10,product_tbl!B:B,product_tbl!A:A,"NO ID FOUND",0) -> V210 | E10: CHICKEN CHEESE BALLS | F10: 3 | G10: 320 | H10: 0 | I10: 320 | J10: 16 | K10: =L10-(I10+J10) -> 9 | L10: 345 | M10: SUCCESS
A11: 322503 | B11: 2026-03-25 | C11: 21:03:35 | D11: =_xlfn.XLOOKUP(E11,product_tbl!B:B,product_tbl!A:A,"NO ID FOUND",0) -> V109 | E11: POTATO CHEESE SHOTZ | F11: 3 | G11: 370 | H11: 0 | I11: 370 | J11: 18.5 | K11: =L11-(I11+J11) -> 9 | L11: 397.5 | M11: SUCCESS
A12: 322722 | B12: 2026-03-27 | C12: 14:03:88 | D12: =_xlfn.XLOOKUP(E12,product_tbl!B:B,product_tbl!A:A,"NO ID FOUND",0) -> V113 | E12: SALTED-FRENCH FRIES | F12: 1 | G12: 110 | H12: 0 | I12: 110 | J12: 5.5 | K12: =L12-(I12+J12) -> 53 | L12: 168.5 | M12: SUCCESS
A13: 323084 | B13: 2026-03-29 | C13: 18:03:31 | D13: =_xlfn.XLOOKUP(E13,product_tbl!B:B,product_tbl!A:A,"NO ID FOUND",0) -> V209 | E13: CHICKEN FINGERS | F13: 2 | G13: 210 | H13: 0 | I13: 210 | J13: 10.5 | K13: =L13-(I13+J13) -> 27 | L13: 247.5 | M13: SUCCESS
A14: 323182 | B14: 2026-03-29 | C14: 21:03:33 | D14: =_xlfn.XLOOKUP(E14,product_tbl!B:B,product_tbl!A:A,"NO ID FOUND",0) -> V108 | E14: VEG-NUGGETS | F14: 2 | G14: 220 | H14: 0 | I14: 220 | J14: 11 | K14: =L14-(I14+J14) -> 19 | L14: 250 | M14: SUCCESS
A15: 323894 | B15: 2026-04-03 | C15: 13:04:12 | D15: =_xlfn.XLOOKUP(E15,product_tbl!B:B,product_tbl!A:A,"NO ID FOUND",0) -> V111 | E15: TANDOORI PANEER NUGGETS | F15: 3 | G15: 350 | H15: 0 | I15: 350 | J15: 17.5 | K15: =L15-(I15+J15) -> 17 | L15: 384.5 | M15: SUCCESS
A16: 323978 | B16: 2026-04-03 | C16: 20:04:84 | D16: =_xlfn.XLOOKUP(E16,product_tbl!B:B,product_tbl!A:A,"NO ID FOUND",0) -> V212 | E16: CHICKEN LOLLIPOP | F16: 2 | G16: 280 | H16: 0 | I16: 280 | J16: 14 | K16: =L16-(I16+J16) -> 19 | L16: 313 | M16: SUCCESS
A17: 324147 | B17: 2026-04-04 | C17: 20:04:22 | D17: =_xlfn.XLOOKUP(E17,product_tbl!B:B,product_tbl!A:A,"NO ID FOUND",0) -> V105 | E17: PANEER MOMOS | F17: 1 | G17: 100 | H17: 0 | I17: 100 | J17: 5 | K17: =L17-(I17+J17) -> 29 | L17: 134 | M17: SUCCESS
A18: 324184 | B18: 2026-04-04 | C18: 21:04:36 | D18: =_xlfn.XLOOKUP(E18,product_tbl!B:B,product_tbl!A:A,"NO ID FOUND",0) -> V202 | E18: CHICKEN CHEESE MOMOS | F18: 2 | G18: 230 | H18: 0 | I18: 230 | J18: 11.5 | K18: =L18-(I18+J18) -> 27 | L18: 268.5 | M18: SUCCESS
A19: 324329 | B19: 2026-04-05 | C19: 18:04:17 | D19: =_xlfn.XLOOKUP(E19,product_tbl!B:B,product_tbl!A:A,"NO ID FOUND",0) -> V102 | E19: CORN & CHEESE MOMOS | F19: 1 | G19: 90 | H19: 0 | I19: 90 | J19: 4.5 | K19: =L19-(I19+J19) -> 37 | L19: 131.5 | M19: SUCCESS
... A66: 333054 | B66: 2026-05-26 | C66: 18:05:42 | D66: =_xlfn.XLOOKUP(E66,product_tbl!B:B,product_tbl!A:A,"NO ID FOUND",0) -> V201 | E66: CHICKEN MOMOS | F66: 2 | G66: 240 | H66: 0 | I66: 240 | J66: 12 | K66: =L66-(I66+J66) -> 19 | L66: 271 | M66: pending

Sheet tabl_product
A1: product_id | B1: product_name | C1: category
A2: V101 | B2: CORN MOMOS | C2: VEG
A3: V102 | B3: CORN & CHEESE MOMOS | C3: VEG
A4: V103 | B4: MIXED-VEG MOMOS | C4: VEG
A5: V104 | B5: VEG-SCHEZWAN MOMOS | C5: VEG
A6: V105 | B6: PANEER MOMOS | C6: VEG
A7: V106 | B7: PANEER TIKKA MOMOS | C7: VEG
A8: V107 | B8: VEG-KURKURE MOMOS | C8: VEG
A9: V108 | B9: VEG-NUGGETS | C9: VEG
A10: V109 | B10: POTATO CHEESE SHOTZ | C10: VEG
A11: V110 | B11: VEG FINGERS | C11: VEG
A12: V111 | B12: TANDOORI PANEER NUGGETS | C12: VEG
... A27: V212 | B27: CHICKEN LOLLIPOP | C27: NON-VEG

Sheet product_tbl
A1: product_id | B1: product_name | C1: category
A2: V101 | B2: CORN MOMOS | C2: VEG
A3: V102 | B3: CORN & CHEESE MOMOS | C3: VEG
A4: V103 | B4: MIXED-VEG MOMOS | C4: VEG
A5: V104 | B5: VEG-SCHEZWAN MOMOS | C5: VEG
A6: V105 | B6: PANEER MOMOS | C6: VEG
A7: V106 | B7: PANEER TIKKA MOMOS | C7: VEG
A8: V107 | B8: VEG-KURKURE MOMOS | C8: VEG
A9: V108 | B9: VEG-NUGGETS | C9: VEG
A10: V109 | B10: POTATO CHEESE SHOTZ | C10: VEG
A11: V110 | B11: VEG FINGERS | C11: VEG
A12: V111 | B12: TANDOORI PANEER NUGGETS | C12: VEG
... A27: V212 | B27: CHICKEN LOLLIPOP | C27: NON-VEG

Sheet CLEANED_DATA
A1: Order_ID | B1: order_date | C1: product_ID | D1: product_name | E1: Quantity | F1: Price | G1: Discount | H1: Amount Afte Discount | I1: GST | J1: Delivery Charges | K1: Total Received Amount | L1: Delivery_status | M1: tabl_product.category
A2: 318778 | B2: 46082 | C2: V201 | D2: CHICKEN MOMOS | E2: 1 | F2: 120 | G2: 0 | H2: 120 | I2: 6 | J2: 29 | K2: 155 | L2: SUCCESS | M2: NON-VEG
A3: 324493 | B3: 46118 | C3: V201 | D3: CHICKEN MOMOS | E3: 3 | F3: 320 | G3: 0 | H3: 320 | I3: 16 | J3: 17 | K3: 353 | L3: SUCCESS | M3: NON-VEG
A4: 324996 | B4: 46121 | C4: V201 | D4: CHICKEN MOMOS | E4: 1 | F4: 110 | G4: 0 | H4: 110 | I4: 5.5 | J4: 37 | K4: 152.5 | L4: SUCCESS | M4: NON-VEG
A5: 325137 | B5: 46122 | C5: V201 | D5: CHICKEN MOMOS | E5: 1 | F5: 110 | G5: 0 | H5: 110 | I5: 5.5 | J5: 37 | K5: 152.5 | L5: SUCCESS | M5: NON-VEG
A6: 325481 | B6: 46124 | C6: V201 | D6: CHICKEN MOMOS | E6: 2 | F6: 220 | G6: 0 | H6: 220 | I6: 11 | J6: 19 | K6: 250 | L6: SUCCESS | M6: NON-VEG
A7: 321991 | B7: 46103 | C7: V101 | D7: CORN MOMOS | E7: 1 | F7: 90 | G7: 0 | H7: 90 | I7: 4.5 | J7: 37 | K7: 131.5 | L7: SUCCESS | M7: VEG
A8: 318836 | B8: 46082 | C8: V208 | D8: CHICKEN NUGGETS | E8: 2 | F8: 250 | G8: 0 | H8: 250 | I8: 12.5 | J8: 19 | K8: 281.5 | L8: SUCCESS | M8: NON-VEG
A9: 324329 | B9: 46117 | C9: V102 | D9: CORN & CHEESE MOMOS | E9: 1 | F9: 90 | G9: 0 | H9: 90 | I9: 4.5 | J9: 37 | K9: 131.5 | L9: SUCCESS | M9: VEG
A10: 321207 | B10: 46098 | C10: V107 | D10: VEG-KURKURE MOMOS | E10: 2 | F10: 240 | G10: 0 | H10: 240 | I10: 12 | J10: 19 | K10: 271 | L10: SUCCESS | M10: VEG
A11: 321436 | B11: 46099 | C11: V110 | D11: VEG FINGERS | E11: 1 | F11: 220 | G11: 0 | H11: 220 | I11: 11 | J11: 19 | K11: 250 | L11: SUCCESS | M11: VEG
A12: 321570 | B12: 46100 | C12: V212 | D12: CHICKEN LOLLIPOP | E12: 2 | F12: 280 | G12: 0 | H12: 280 | I12: 14 | J12: 19 | K12: 313 | L12: SUCCESS | M12: NON-VEG
A13: 323978 | B13: 46115 | C13: V212 | D13: CHICKEN LOLLIPOP | E13: 2 | F13: 280 | G13: 0 | H13: 280 | I13: 14 | J13: 19 | K13: 313 | L13: SUCCESS | M13: NON-VEG
... A66: 333054 | B66: 46168 | C66: V201 | D66: CHICKEN MOMOS | E66: 2 | F66: 240 | G66: 0 | H66: 240 | I66: 12 | J66: 19 | K66: 271 | L66: pending | M66: NON-VEG

Sheet KPI'S
A1: KEY PERFORMANCE INDICATORS
A2: SUM OF TOTAL AMOUNT | B2: =SUM(Orders_tbl!L:L) -> 15844.5
A3: COUNT OF TOTAL ORDERS | B3: =COUNTA(Orders_tbl!A:A) -> 66

Sheet PIVOT_TABLE
A1: SALES BY CATEGORY
A3: Row Labels | B3: Sum of Total Received Amount
A4: NON-VEG | B4: 9994.5
A5: VEG | B5: 5850
A6: Grand Total | B6: 15844.5
A16: SALE BY PRODUCT NAME
A19: Row Labels | B19: Sum of Total Received Amount
A20: BUTTER CHICKEN MOMOS | B20: 550
A21: CHICKEN CHEESE BALLS | B21: 616
A22: CHICKEN CHEESE MOMOS | B22: 2041.5
A23: CHICKEN FINGERS | B23: 718.5
A24: CHICKEN KURKURE MOMOS | B24: 176
A25: CHICKEN LOLLIPOP | B25: 626
A26: CHICKEN MOMOS | B26: 2235.5
A27: CHICKEN NUGGETS | B27: 831.5
A28: CHICKEN PERI PERI MOMOS | B28: 760.5
A29: CHICKEN POPCORN | B29: 1284
A30: CHICKEN TIKKA MOMOS | B30: 155
A31: CORN & CHEESE MOMOS | B31: 960.5
... A45: Grand Total | B45: 15844.5

Sheet DASHBOARD
A1: CAFÉ DATA SALES ANALYSIS DASHBOARD
A3: SUM OF TOTAL AMOUNT | B3: =SUM(Orders_tbl!L:L) -> 15844.5
A4: COUNT OF TOTAL ORDERS | B4: =COUNTA(Orders_tbl!A:A) -> 66
